serviceb_client/__init__.py
serviceb_client/api_client.py
serviceb_client/configuration.py
serviceb_client/exceptions.py
serviceb_client/model_utils.py
serviceb_client/rest.py
serviceb_client/api/__init__.py
serviceb_client/api/genres_api.py
serviceb_client/api/lists_api.py
serviceb_client/api/movies_api.py
serviceb_client/api/oauth2_api.py
serviceb_client/api/users_api.py
serviceb_client/apis/__init__.py
serviceb_client/model/__init__.py
serviceb_client/model/genre.py
serviceb_client/model/http_validation_error.py
serviceb_client/model/list_create.py
serviceb_client/model/list_schema.py
serviceb_client/model/list_update.py
serviceb_client/model/movie.py
serviceb_client/model/token.py
serviceb_client/model/user.py
serviceb_client/model/user_create.py
serviceb_client/model/user_update.py
serviceb_client/model/validation_error.py
serviceb_client/models/__init__.py
serviceb_client-1.0.0.dist-info/METADATA
serviceb_client-1.0.0.dist-info/WHEEL
serviceb_client-1.0.0.dist-info/top_level.txt
serviceb_client-1.0.0.dist-info/RECORD
